Workbook

Sheet README
A1: TenderOS Enterprise: features by jouleWise and client responsibility
A3: One row per feature on the Features sheet. For each: what jouleWise does (green column) and what the client does (yellow column).
A4: jouleWise: builds, tests, signs and ships the software, keeps the norms and tender packs current, and patches under the AMC.
A5: Client: provides the inputs and evidence, runs the installation on its own hardware, reviews and signs off, and submits the bid.
A7: Columns
A8: ID · Area · Feature · What it does · Client team (which client team fills it in or owns it) · Zone · Status · Priority · jouleWise · Client · Notes / where
A10: Zone
A11: DMZ: Tender intake zone: internet-facing, holds the tender documents and the cloud LLMs; no bid data
A12: Core: Militarised zone: the client's network, TenderOS with the bid, the engine and the model; no cloud LLM
A13: Both: Present in both zones
A15: Status
A16: Live: In TenderOS Demo 2 today
... A36: Built by tools/build_features_split.py from the list in tools/build_enterprise_features.py.

Sheet Features
A1: ID | B1: Area | C1: Feature | D1: What it does | E1: Client team | F1: Zone | G1: Status | H1: Priority | I1: jouleWise | J1: Client | K1: Notes / where
A2: TI-01 | B2: Tender intake | C2: Upload a tender | D2: Any power tender (PDF, Word, text, to 60 MB); the type is detected or chosen | E2: Legal | F2: DMZ | G2: Live | H2: P1 | I2: Builds and maintains the reading engine (parsers, extraction models, prompts) and the intake-zone screens; ships fixes under AMC | J2: Uploads the tender documents in the intake zone; Legal reviews the reading (every value on its page) before it is packaged for the core | K2: Tender to Bid start screen
A3: TI-02 | B3: Tender intake | C3: Upload a tender set | D3: RfS with amendments, clarifications and PPA/PSA (to 20 files): amendments applied to the RfS | E3: Legal | F3: DMZ | G3: Live | H3: P1 | I3: Builds and maintains the reading engine (parsers, extraction models, prompts) and the intake-zone screens; ships fixes under AMC | J3: Uploads the tender documents in the intake zone; Legal reviews the reading (every value on its page) before it is packaged for the core | K3: engine/extraction/tenderset
A4: TI-03 | B4: Tender intake | C4: LLM reading of the tender | D4: Every value with page and quote; sections mapped; scan screen with five agents | E4: Legal | F4: DMZ | G4: Live | H4: P1 | I4: Builds and maintains the reading engine (parsers, extraction models, prompts) and the intake-zone screens; ships fixes under AMC | J4: Uploads the tender documents in the intake zone; Legal reviews the reading (every value on its page) before it is packaged for the core | K4: Claude (claude-fable-5-1) through engine/extraction; rule-based reader without a key
A5: TI-04 | B5: Tender intake | C5: Table reading (Docling) | D5: Amendment and clarification tables through docling-serve; PyMuPDF fallback | E5: Legal | F5: DMZ | G5: Live | H5: P1 | I5: Builds and maintains the reading engine (parsers, extraction models, prompts) and the intake-zone screens; ships fixes under AMC | J5: Uploads the tender documents in the intake zone; Legal reviews the reading (every value on its page) before it is packaged for the core
A6: TI-05 | B6: Tender intake | C6: Scanned pages (LlamaParse) | D6: Pages without a text layer read through LlamaParse | E6: Legal | F6: DMZ | G6: Live | H6: P2 | I6: Builds and maintains the reading engine (parsers, extraction models, prompts) and the intake-zone screens; ships fixes under AMC | J6: Uploads the tender documents in the intake zone; Legal reviews the reading (every value on its page) before it is packaged for the core | K6: Optional key
A7: TI-06 | B7: Tender intake | C7: Amendments: changes was → now | D7: Each clause before and after, with quotes, word diff and effect | E7: Legal | F7: DMZ | G7: Live | H7: P1 | I7: Builds and maintains the reading engine (parsers, extraction models, prompts) and the intake-zone screens; ships fixes under AMC | J7: Uploads the tender documents in the intake zone; Legal reviews the reading (every value on its page) before it is packaged for the core
A8: TI-07 | B8: Tender intake | C8: Clarifications with verdicts | D8: SECI's answers linked to the clauses, accepted / refused | E8: Legal | F8: DMZ | G8: Live | H8: P1 | I8: Builds and maintains the reading engine (parsers, extraction models, prompts) and the intake-zone screens; ships fixes under AMC | J8: Uploads the tender documents in the intake zone; Legal reviews the reading (every value on its page) before it is packaged for the core
A9: TI-08 | B9: Tender intake | C9: Consolidated reading | D9: RfS fields with amendments applied and their history | E9: Legal | F9: DMZ | G9: Live | H9: P1 | I9: Builds and maintains the reading engine (parsers, extraction models, prompts) and the intake-zone screens; ships fixes under AMC | J9: Uploads the tender documents in the intake zone; Legal reviews the reading (every value on its page) before it is packaged for the core
A10: TI-09 | B10: Tender intake | C10: Bid formats and bid process | D10: Formats with blanks and context; the bid steps from registration to PPA | E10: Legal | F10: DMZ | G10: Live | H10: P1 | I10: Builds and maintains the reading engine (parsers, extraction models, prompts) and the intake-zone screens; ships fixes under AMC | J10: Uploads the tender documents in the intake zone; Legal reviews the reading (every value on its page) before it is packaged for the core
A11: TI-10 | B11: Tender intake | C11: Search over the tender | D11: BM25 search over every page of the set | E11: All | F11: DMZ | G11: Live | H11: P2 | I11: Builds and maintains the reading engine (parsers, extraction models, prompts) and the intake-zone screens; ships fixes under AMC | J11: Uploads the tender documents in the intake zone; Legal reviews the reading (every value on its page) before it is packaged for the core | K11: Haystack
A12: TI-11 | B12: Tender intake | C12: Curated tender packs | D12: A reviewed pack per tender (SECI FDRE-RTC-V): conditions, changes, clarifications, formats, every quote checked on its page | E12: Legal | F12: DMZ | G12: Live | H12: P1 | I12: Builds and maintains the reading engine (parsers, extraction models, prompts) and the intake-zone screens; ships fixes under AMC | J12: Uploads the tender documents in the intake zone; Legal reviews the reading (every value on its page) before it is packaged for the core | K12: web/src/seci/seci-rtc-tm-v.json; tests/test_seci_pack.py
A13: TI-12 | B13: Tender intake | C13: Pre-bid queries | D13: Points to raise with the issuer, each quoting the clause and page; Word file | E13: Legal | F13: DMZ | G13: Live | H13: P2 | I13: Builds and maintains the reading engine (parsers, extraction models, prompts) and the intake-zone screens; ships fixes under AMC | J13: Uploads the tender documents in the intake zone; Legal reviews the reading (every value on its page) before it is packaged for the core
A14: TI-13 | B14: Tender intake | C14: Tender questions by voice / chat | D14: Ask the extracted tender questions; answers cite document and page | E14: All | F14: DMZ | G14: Extend | H14: P2 | I14: Builds and maintains the reading engine (parsers, extraction models, prompts) and the intake-zone screens; ships fixes under AMC | J14: Uploads the tender documents in the intake zone; Legal reviews the reading (every value on its page) before it is packaged for the core | K14: GPT-Live bid agent today also drives the bid; in the DMZ it answers tender questions only
A15: TI-14 | B15: Tender intake | C15: CERC orders | D15: Tariff-adoption orders uploaded and read into facts with page and quote; SECI results as reported | E15: Finance | F15: DMZ | G15: Live | H15: P3 | I15: Builds and maintains the reading engine (parsers, extraction models, prompts) and the intake-zone screens; ships fixes under AMC | J15: Uploads the tender documents in the intake zone; Legal reviews the reading (every value on its page) before it is packaged for the core | K15: Recent tenders tab
A16: TI-15 | B16: Tender intake | C16: Claude connector (MCP) | D16: TenderOS tools in Claude: tender lookup with citations, sizing, financials, What-if | E16: All | F16: DMZ | G16: Extend | H16: P3 | I16: Provides the connector and its tools; off in the core by default | J16: Decides whether the connector is allowed in the intake zone; manages the token | K16: Demo only; in the enterprise version limited to the tender (no bid data) or off
A17: TI-16 | B17: Tender intake | C17: Review before transfer | D17: A reviewer confirms the reading (every value located on its page) before it is packaged for the core | E17: Legal | F17: DMZ | G17: Build | H17: P1 | I17: Builds the review screen with every value on its page | J17: Legal reviews and confirms the reading before transfer | K17: Today: the reviewer ticks unlocated values in the workflow
A18: TI-17 | B18: Tender intake | C18: Transfer package to the core | D18: The reading, the pack and the documents exported as one signed, checksummed bundle; imported inside the core | E18: IT | F18: Both | G18: Build | H18: P1 | I18: Builds the signed package format, the export and the import tool | J18: IT carries the package across the one-way transfer (file drop or diode) and imports it in the core | K18: One-way: documents in, nothing out
A19: BW-01 | B19: Bid workspace | C19: Step-wise bid navigation | D19: One tender, one bid, steps in order with sign-off per step: Tender → Bid inputs → Design → Finance inputs → Sizing → Results → Financial model → What-if → Bid forms → Submission | E19: All | F19: Core | G19: Live | H19: P1 | I19: Builds, tests and patches the bid workspace; keeps the steps, benchmarks and tender packs current | J19: Projects, Design, Finance and Legal enter their inputs step by step, attach evidence and sign off; the tender manager runs the bid | K19: SECI RTC tab: Tender → Conditions → Bid inputs (Projects) → Design → Finance inputs → Size → Financial model → What-if → Bid forms → Winning bid, each step labelled with its team; sign-off is per box (Evidence)
A20: BW-02 | B20: Bid workspace | C20: Team-wise input tabs | D20: Projects (bid inputs and assumptions), Design and Finance each get their own input tab; each box shows who owns it and whether it is filled, evidenced and signed off | E20: All | F20: Core | G20: Live | H20: P1 | I20: Builds, tests and patches the bid workspace; keeps the steps, benchmarks and tender packs current | J20: Projects, Design, Finance and Legal enter their inputs step by step, attach evidence and sign off; the tender manager runs the bid | K20: Bid inputs (Projects), Design, Finance inputs as steps of their own; the paperclip on every box shows evidence and sign-off
A21: BW-03 | B21: Bid workspace | C21: Bid inputs and assumptions (Projects) | D21: Contracted MW, dates, supply profile and planning choices (Peak Hours, shortfall), market sale, assumptions register | E21: Projects | F21: Core | G21: Live | H21: P1 | I21: Builds, tests and patches the bid workspace; keeps the steps, benchmarks and tender packs current | J21: Projects, Design, Finance and Legal enter their inputs step by step, attach evidence and sign off; the tender manager runs the bid | K21: The Bid inputs step; the assumptions register is the evidence register
A22: BW-04 | B22: Bid workspace | C22: Benchmarks | D22: Industry benchmarks (CERC norms, market prices) fill empty inputs, marked as benchmarks until changed | E22: All | F22: Core | G22: Live | H22: P1 | I22: Keeps the CERC norms and market prices current in the benchmarks | J22: Replaces benchmarks with its own numbers and evidence
A23: BW-05 | B23: Bid workspace | C23: Tender conditions checklist | D23: Every condition against the bid: met, failed, pending; with page and quote | E23: Legal | F23: Core | G23: Live | H23: P1 | I23: Builds, tests and patches the bid workspace; keeps the steps, benchmarks and tender packs current | J23: Projects, Design, Finance and Legal enter their inputs step by step, attach evidence and sign off; the tender manager runs the bid
A24: BW-06 | B24: Bid workspace | C24: Saved bids with versions | D24: A bid saved to the library with versions; opened later; compared | E24: Management | F24: Core | G24: Live | H24: P1 | I24: Builds, tests and patches the bid workspace; keeps the steps, benchmarks and tender packs current | J24: Projects, Design, Finance and Legal enter their inputs step by step, attach evidence and sign off; the tender manager runs the bid | K24: Scenario library
A25: BW-07 | B25: Bid workspace | C25: Sign-off per step and submission lock | D25: Each team signs off its step; the manager freezes the bid for submission; later edits make a new version | E25: Management | F25: Core | G25: Build | H25: P2 | I25: Builds, tests and patches the bid workspace; keeps the steps, benchmarks and tender packs current | J25: Projects, Design, Finance and Legal enter their inputs step by step, attach evidence and sign off; the tender manager runs the bid
A26: BW-08 | B26: Bid workspace | C26: Bid forms and letters | D26: Every RfS format filled from the bid, reviewed beside its page; letters in the RfS wording, editable; Word and PDF; the bid pack | E26: Legal | F26: Core | G26: Live | H26: P1 | I26: Builds every format and letter of each tender pack | J26: Legal reviews, edits the wording and signs the pack | K26: SECI formats today; other tenders through their packs
A27: BW-09 | B27: Bid workspace | C27: Winning bid analysis | D27: The auction result and a bridge from the benchmark tariff to it, lever by lever | E27: Management | F27: Core | G27: Live | H27: P3 | I27: Builds, tests and patches the bid workspace; keeps the steps, benchmarks and tender packs current | J27: Projects, Design, Finance and Legal enter their inputs step by step, attach evidence and sign off; the tender manager runs the bid
A28: D-01 | B28: Design | C28: Supply sources | D28: Solar, wind, battery, biomass, hydro, thermal with costs, limits and fixed sizes | E28: Design | F28: Core | G28: Live | H28: P1 | I28: Builds the design tools (sources, studios, profiles, schematic, losses, DSM model) and keeps the engineering norms current | J28: Design team provides the CUF files, costs, site layout and losses, with evidence; validates the DSM norms against the regulations in force
A29: D-02 | B29: Design | C29: Solar plant studio | D29: Layout from modules, mounting, string or central inverters; cost in ₹/Wp; writes the cost into the bid | E29: Design | F29: Core | G29: Live | H29: P2 | I29: Builds the design tools (sources, studios, profiles, schematic, losses, DSM model) and keeps the engineering norms current | J29: Design team provides the CUF files, costs, site layout and losses, with evidence; validates the DSM norms against the regulations in force
A30: D-03 | B30: Design | C30: Wind farm studio | D30: Turbines by make, CUF at the site's wind, farm cost; writes the cost into the bid | E30: Design | F30: Core | G30: Live | H30: P2 | I30: Builds the design tools (sources, studios, profiles, schematic, losses, DSM model) and keeps the engineering norms current | J30: Design team provides the CUF files, costs, site layout and losses, with evidence; validates the DSM norms against the regulations in force
A31: D-04 | B31: Design | C31: Profiles: upload and view | D31: Hourly solar and wind profiles uploaded; CUF, month × hour heat map, monthly CUF, a week | E31: Design | F31: Core | G31: Live | H31: P1 | I31: Builds the design tools (sources, studios, profiles, schematic, losses, DSM model) and keeps the engineering norms current | J31: Design team provides the CUF files, costs, site layout and losses, with evidence; validates the DSM norms against the regulations in force
A32: D-05 | B32: Design | C32: CUF file download | D32: Download the profile used in the bid (as uploaded, and as scaled to the CUF entered) with its statistics | E32: Design | F32: Core | G32: Live | H32: P1 | I32: Builds the download | J32: Design keeps the file with the bid pack as evidence | K32: CSV built in the browser; tools/check_cuf_file.mjs
A33: D-06 | B33: Design | C33: 25-year CUF justification | D33: Why one year's profile stands for 25: the source and period of the data, P50/P90, degradation per year, inter-annual variability, the typical year method; a note in the bid pack | E33: Design | F33: Core | G33: Live | H33: P1 | I33: Builds the justification note and the Word export | J33: Design provides the data source, period, P50/P90 report and the assessor's name | K33: Panel on the profile with P50/P90 inputs; Word file from POST /api/plant/justification
A34: D-07 | B34: Design | C34: Losses to the billing meter | D34: Each technology's stages to the 33 kV bus with where its CUF is measured; the 33/220 kV transformer and the line | E34: Design | F34: Core | G34: Live | H34: P1 | I34: Builds the design tools (sources, studios, profiles, schematic, losses, DSM model) and keeps the engineering norms current | J34: Design team provides the CUF files, costs, site layout and losses, with evidence; validates the DSM norms against the regulations in force
A35: D-08 | B35: Design | C35: Separate sites | D35: Solar and wind on different sites, each with its own battery; no energy between them | E35: Design | F35: Core | G35: Live | H35: P1 | I35: Builds the design tools (sources, studios, profiles, schematic, losses, DSM model) and keeps the engineering norms current | J35: Design team provides the CUF files, costs, site layout and losses, with evidence; validates the DSM norms against the regulations in force
A36: D-09 | B36: Design | C36: Co-located solar + BESS and wind + BESS | D36: Which site each battery sits on and charges from; one or two pooling stations | E36: Design | F36: Core | G36: Live | H36: P1 | I36: Builds the design tools (sources, studios, profiles, schematic, losses, DSM model) and keeps the engineering norms current | J36: Design team provides the CUF files, costs, site layout and losses, with evidence; validates the DSM norms against the regulations in force | K36: One site (shared pooling station) or separate sites, each with its own battery and pooling station; the losses of each reach the sizing
A37: D-10 | B37: Design | C37: Site schematic (single-line) | D37: A drawing of the chosen layout: solar, wind and battery blocks, their transformers, the pooling station(s), the line to the billing meter; losses shown at each stage and summed at the pooling station | E37: Design | F37: Core | G37: Live | H37: P1 | I37: Builds the design tools (sources, studios, profiles, schematic, losses, DSM model) and keeps the engineering norms current | J37: Design team provides the CUF files, costs, site layout and losses, with evidence; validates the DSM norms against the regulations in force | K37: bid/SiteSchematic.jsx: one or two pooling stations with their transformer and line losses; inputs beside the drawing
A38: D-11 | B38: Design | C38: Deviation settlement (DSM) per CERC | D38: Forecast error on solar and wind by block, the DSM charges under the CERC DSM Regulations (bands by % deviation, the RE schedule revision allowance), a forecasting accuracy input, the cost in the model | E38: Design | F38: Core | G38: Live | H38: P1 | I38: Builds the DSM model with editable norms and keeps the regulations' structure current | J38: Design and Finance set the forecast-error and the norms from the notified text; validate against their DSM bills | K38: src/dsm: forecast-error distribution, tolerance band by year, X factor trajectory, steps beyond the band; norms editable; verify against the notified text
A39: D-12 | B39: Design | C39: Degradation and augmentation | D39: Solar, wind and battery degradation; battery augmentation annual or one-time with price decline | E39: Design | F39: Core | G39: Live | H39: P1 | I39: Builds the design tools (sources, studios, profiles, schematic, losses, DSM model) and keeps the engineering norms current | J39: Design team provides the CUF files, costs, site layout and losses, with evidence; validates the DSM norms against the regulations in force
A40: S-01 | B40: Sizing | C40: Sizing engine | D40: The least-tariff plant that meets every tender condition over the PPA term; a seed from the last sizing | E40: Design | F40: Core | G40: Live | H40: P1 | I40: Owns the optimizer (jouleWise IP, delivered sealed), its performance and its tuning; supports runs under AMC | J40: Runs the sizing on its own hardware; reviews the sizes and the compliance with the tender | K40: Proprietary; described by its interface only
A41: S-02 | B41: Sizing | C41: Tender supply rules | D41: Annual, monthly and time-block floors (every 15-minute block), peak hours as planned (costliest IEX hours, any of the window, evening), shortfall at a penalty or hard | E41: Projects | F41: Core | G41: Live | H41: P1 | I41: Owns the optimizer (jouleWise IP, delivered sealed), its performance and its tuning; supports runs under AMC | J41: Runs the sizing on its own hardware; reviews the sizes and the compliance with the tender
A42: S-03 | B42: Sizing | C42: Market sale of surplus | D42: Sales on IEX (hourly DAM/G-DAM prices) or at a flat price; PPA first; buyer's first right at a share of the tariff | E42: Projects | F42: Core | G42: Live | H42: P1 | I42: Owns the optimizer (jouleWise IP, delivered sealed), its performance and its tuning; supports runs under AMC | J42: Runs the sizing on its own hardware; reviews the sizes and the compliance with the tender
A43: S-04 | B43: Sizing | C43: 15-minute dispatch, every PPA year | D43: Block-wise dispatch with ramp and minimum, every floor checked, CSV/ZIP and Excel | E43: Design | F43: Core | G43: Live | H43: P1 | I43: Owns the optimizer (jouleWise IP, delivered sealed), its performance and its tuning; supports runs under AMC | J43: Runs the sizing on its own hardware; reviews the sizes and the compliance with the tender
A44: S-05 | B44: Sizing | C44: Dispatch sheets in Excel | D44: Every modelled year hour by hour as formulas; the yearly energy of the model comes from them | E44: Finance | F44: Core | G44: Live | H44: P1 | I44: Owns the optimizer (jouleWise IP, delivered sealed), its performance and its tuning; supports runs under AMC | J44: Runs the sizing on its own hardware; reviews the sizes and the compliance with the tender
A45: S-06 | B45: Sizing | C45: Compliance table and hourly charts | D45: Floors met per year, the week's dispatch, the per-hour Sankey of where energy went | E45: All | F45: Core | G45: Live | H45: P1 | I45: Owns the optimizer (jouleWise IP, delivered sealed), its performance and its tuning; supports runs under AMC | J45: Runs the sizing on its own hardware; reviews the sizes and the compliance with the tender
A46: F-01 | B46: Finance | C46: Financing inputs (Finance tab) | D46: Target equity IRR, debt share, rate, tenor, repayment, tax, depreciation, O&M escalation, insurance, receivables, discount rate | E46: Finance | F46: Core | G46: Live | H46: P1 | I46: Builds the 25-year financial model and its Excel twin, checked against LibreOffice; keeps tax and CERC norms current | J46: Finance team provides the financing terms, lender's conditions and working-capital norms, with evidence; validates against its own model | K46: The Finance inputs step of the SECI flow (and the Financials step of every tab)
A47: F-02 | B47: Finance | C47: 25-year financial model | D47: Revenue, penalties, O&M, insurance, augmentation, depreciation (WDV/SLM), tax with loss carry-forward, debt, DSCR, IRRs, LCOE, payback | E47: Finance | F47: Core | G47: Live | H47: P1 | I47: Builds the 25-year financial model and its Excel twin, checked against LibreOffice; keeps tax and CERC norms current | J47: Finance team provides the financing terms, lender's conditions and working-capital norms, with evidence; validates against its own model
A48: F-03 | B48: Finance | C48: Tariff for the target IRR | D48: The tariff that gives the target equity IRR; a quoted tariff's equity and project IRR with a warning below target | E48: Finance | F48: Core | G48: Live | H48: P1 | I48: Builds the 25-year financial model and its Excel twin, checked against LibreOffice; keeps tax and CERC norms current | J48: Finance team provides the financing terms, lender's conditions and working-capital norms, with evidence; validates against its own model
A49: F-04 | B49: Finance | C49: Traceable model | D49: Every number's formula, precedents, dependents and the inputs it rests on, in the app | E49: Finance | F49: Core | G49: Live | H49: P1 | I49: Builds the 25-year financial model and its Excel twin, checked against LibreOffice; keeps tax and CERC norms current | J49: Finance team provides the financing terms, lender's conditions and working-capital norms, with evidence; validates against its own model
A50: F-05 | B50: Finance | C50: Excel model with live formulas | D50: The whole model as Excel formulas (Live model sheet), recalculated by LibreOffice in tests to the app's numbers | E50: Finance | F50: Core | G50: Live | H50: P1 | I50: Builds the 25-year financial model and its Excel twin, checked against LibreOffice; keeps tax and CERC norms current | J50: Finance team provides the financing terms, lender's conditions and working-capital norms, with evidence; validates against its own model
A51: F-06 | B51: Finance | C51: Construction phase, monthly | D51: Monthly model from financial closure to commissioning: drawdown schedule, equity first or pro rata, capex phasing by package, commissioning in parts | E51: Finance | F51: Core | G51: Live | H51: P1 | I51: Builds the 25-year financial model and its Excel twin, checked against LibreOffice; keeps tax and CERC norms current | J51: Finance team provides the financing terms, lender's conditions and working-capital norms, with evidence; validates against its own model | K51: Months, drawdown profile (even, S-curve, front, back), equity first or pro rata; Construction sheet in Excel. Phasing by package and commissioning in parts: not built
A52: F-07 | B52: Finance | C52: Interest during construction (IDC) | D52: IDC computed month by month from the drawdowns and the rate, capitalised into the project cost (today a % of hard cost) | E52: Finance | F52: Core | G52: Live | H52: P1 | I52: Builds the 25-year financial model and its Excel twin, checked against LibreOffice; keeps tax and CERC norms current | J52: Finance team provides the financing terms, lender's conditions and working-capital norms, with evidence; validates against its own model | K52: Month by month on the debt drawn, capitalised as debt; 0 months keeps the pre-operative % as before
A53: F-08 | B53: Finance | C53: Operations phase, yearly | D53: The yearly model starts at commissioning (COD) with the construction balances carried in | E53: Finance | F53: Core | G53: Live | H53: P1 | I53: Builds the 25-year financial model and its Excel twin, checked against LibreOffice; keeps tax and CERC norms current | J53: Finance team provides the financing terms, lender's conditions and working-capital norms, with evidence; validates against its own model | K53: Year 1 starts at COD with the debt (incl. IDC) and equity from the construction schedule
A54: F-09 | B54: Finance | C54: Working capital | D54: Receivables (days), O&M stock, maintenance spares, DSM and penalty reserve; working capital loan with its own rate and margin; letter of credit cost | E54: Finance | F54: Core | G54: Live | H54: P1 | I54: Builds the 25-year financial model and its Excel twin, checked against LibreOffice; keeps tax and CERC norms current | J54: Finance team provides the financing terms, lender's conditions and working-capital norms, with evidence; validates against its own model | K54: Receivable days, O&M in hand (months), spares (% of O&M), interest on the working capital, DSRA. DSM/penalty reserve and letter-of-credit cost: not built
A55: F-10 | B55: Finance | C55: Repayment methods | D55: Equal principal, annuity, sculpted to a target DSCR, balloon / bullet, step-up; grace period / moratorium; quarterly or yearly instalments | E55: Finance | F55: Core | G55: Live | H55: P1 | I55: Builds the 25-year financial model and its Excel twin, checked against LibreOffice; keeps tax and CERC norms current | J55: Finance team provides the financing terms, lender's conditions and working-capital norms, with evidence; validates against its own model | K55: Equal, annuity, sculpted, balloon, bullet, step-up; moratorium; yearly, half-yearly, quarterly or monthly instalments; all as Excel formulas
A56: F-11 | B56: Finance | C56: Debt sculpting | D56: Principal shaped to hold a target DSCR each year given CFADS; minimum and average DSCR reported | E56: Finance | F56: Core | G56: Live | H56: P1 | I56: Builds the 25-year financial model and its Excel twin, checked against LibreOffice; keeps tax and CERC norms current | J56: Finance team provides the financing terms, lender's conditions and working-capital norms, with evidence; validates against its own model | K56: Principal = CFADS ÷ target DSCR − interest each year; the last year clears the balance
A57: F-12 | B57: Finance | C57: Refinancing | D57: Refinance in a chosen year at a new rate and tenor, with fees and prepayment cost; before/after returns | E57: Finance | F57: Core | G57: Live | H57: P1 | I57: Builds the 25-year financial model and its Excel twin, checked against LibreOffice; keeps tax and CERC norms current | J57: Finance team provides the financing terms, lender's conditions and working-capital norms, with evidence; validates against its own model | K57: Year, new rate, new tenor, fee on the balance; the schedule continues under the same method. Prepayment cost: use the fee
A58: F-13 | B58: Finance | C58: DSCR and lender's view | D58: Minimum and average DSCR, lender's IRR, DSRA, covenants flagged | E58: Finance | F58: Core | G58: Live | H58: P1 | I58: Builds the 25-year financial model and its Excel twin, checked against LibreOffice; keeps tax and CERC norms current | J58: Finance team provides the financing terms, lender's conditions and working-capital norms, with evidence; validates against its own model | K58: Min/avg DSCR, DSRA, lender's IRR (What-if); DSCR below 1.1 flagged red. Covenant list: not built
A59: F-14 | B59: Finance | C59: Deviation settlement cost in the model | D59: The DSM charges from the Design tab as an operating cost line | E59: Finance | F59: Core | G59: Live | H59: P1 | I59: Builds the 25-year financial model and its Excel twin, checked against LibreOffice; keeps tax and CERC norms current | J59: Finance team provides the financing terms, lender's conditions and working-capital norms, with evidence; validates against its own model | K59: DSM charges as an operating-cost line, a line in the year's tariff; in the Excel model as formulas
A60: F-15 | B60: Finance | C60: Money at stake | D60: EMD, PBG and net worth on the installed capacity | E60: Finance | F60: Core | G60: Live | H60: P1 | I60: Builds the 25-year financial model and its Excel twin, checked against LibreOffice; keeps tax and CERC norms current | J60: Finance team provides the financing terms, lender's conditions and working-capital norms, with evidence; validates against its own model | K60: Per tender pack
A61: W-01 | B61: What-if | C61: What-if after sizing | D61: Opens on the sized plant: the optimum as the base case, every input as a lever | E61: All | F61: Core | G61: Live | H61: P1 | I61: Builds the What-if and the tariff levers; keeps them in step with the model | J61: Management and Finance use them on bid day to decide the tariff to quote | K61: The What-if step of the SECI flow starts from the sized plant and every input of the bid
A62: W-02 | B62: What-if | C62: Tariff levers on bid day | D62: Set a tariff and see which levers reach it: cost, CUF, financing, IRR, storage, sale; each lever's effect on the tariff and the IRR; instant | E62: Management | F62: Core | G62: Live | H62: P1 | I62: Builds the What-if and the tariff levers; keeps them in step with the model | J62: Management and Finance use them on bid day to decide the tariff to quote | K62: whatif/levers.js: each lever's tariff a step up and down, ₹/kWh per step, the move of that lever alone to reach the tariff wanted; Apply
... A67: E-03 | B67: Evidence | C67: Evidence status on every box | D67: Each box shows filled / evidenced / signed off; the bid pack lists the evidence register | E67: All | F67: Core | G67: Live | H67: P1 | I67: Builds evidence, sign-off, the register and the audit log; patches them under AMC | J67: Every team attaches evidence to its inputs; the super admin signs values off; IT keeps the exports | K67: Faint / with count / signed off at this value / signed at an older value; the register as CSV
A68: E-04 | B68: Evidence | C68: Assignments | D68: A data point assigned to a team or person; answer with a value, note or file; accept or return into the bid as a new version | E68: All | F68: Core | G68: Live | H68: P1 | I68: Builds evidence, sign-off, the register and the audit log; patches them under AMC | J68: Every team attaches evidence to its inputs; the super admin signs values off; IT keeps the exports
A69: E-05 | B69: Evidence | C69: Pings from any box (@mentions) | D69: A thread on every input box; mention a teammate; reply with a value; Fill in | E69: All | F69: Core | G69: Live | H69: P1 | I69: Builds evidence, sign-off, the register and the audit log; patches them under AMC | J69: Every team attaches evidence to its inputs; the super admin signs values off; IT keeps the exports
A70: E-06 | B70: Evidence | C70: Team setup | D70: People, teams, super admin, titles, the tabs they cover | E70: Management | F70: Core | G70: Live | H70: P1 | I70: Builds evidence, sign-off, the register and the audit log; patches them under AMC | J70: Every team attaches evidence to its inputs; the super admin signs values off; IT keeps the exports
A71: E-07 | B71: Evidence | C71: Activity and audit log | D71: Every sizing, export and change logged with user and time; exportable | E71: IT | F71: Core | G71: Extend | H71: P2 | I71: Builds evidence, sign-off, the register and the audit log; patches them under AMC | J71: Every team attaches evidence to its inputs; the super admin signs values off; IT keeps the exports | K71: Activity log today; export to build
A72: E-08 | B72: Evidence | C72: Email notifications | D72: Assignments and pings by email through the client's SMTP | E72: All | F72: Core | G72: Live | H72: P2 | I72: Builds evidence, sign-off, the register and the audit log; patches them under AMC | J72: Every team attaches evidence to its inputs; the super admin signs values off; IT keeps the exports
A73: P-01 | B73: Platform | C73: Users, sign-in and tab access | D73: Accounts, administrator, tabs granted per user | E73: IT | F73: Both | G73: Live | H73: P1 | I73: Builds accounts, roles and tab access | J73: IT creates users, grants tabs and removes leavers
A74: P-02 | B74: Platform | C74: Enterprise sign-in (SSO) | D74: The client's directory (SAML/OIDC or LDAP) for sign-in | E74: IT | F74: Core | G74: Build | H74: P2 | I74: Integrates SAML/OIDC or LDAP | J74: IT provides the identity provider, the metadata and the groups
A75: P-03 | B75: Platform | C75: Air-gapped installation | D75: Everything as an offline bundle: images, database, no outbound traffic from the core; verified checksums | E75: IT | F75: Core | G75: Live | H75: P1 | I75: Builds the offline bundle (images, compose, migrations, checksums, signature) and the installer | J75: IT provides the servers, Docker, the certificate and the firewall rules; installs with install.sh | K75: deploy/enterprise: images.tar, compose overlay with internal networks, install.sh; not run against a Docker daemon in this session
A76: P-04 | B76: Platform | C76: Patches under AMC | D76: Signed offline patch bundles from jouleWise, applied by the client's IT with one command, with health check and rollback; a changelog per patch | E76: IT | F76: Core | G76: Live | H76: P1 | I76: Signs and ships each patch bundle with its changelog; supports the apply and any rollback | J76: IT verifies and applies the bundle with tenderos-patch; keeps the backups it makes | K76: tenderos-patch verify/apply/rollback/status on signed bundles (manifest + ECDSA signature); apply/rollback not exercised against a Docker daemon here
A77: P-05 | B77: Platform | C77: Backups and restore | D77: Database and files backed up on a schedule; restore tested | E77: IT | F77: Core | G77: Live | H77: P1 | I77: Provides the backup and restore scripts and tests them | J77: IT schedules the backups, stores them off the server and tests a restore | K77: deploy/backup.sh today
A78: P-06 | B78: Platform | C78: HTTPS and firewall | D78: TLS at the edge; allowlists | E78: IT | F78: Both | G78: Live | H78: P1 | I78: Configures TLS at the edge and documents the rules per zone | J78: IT provides the certificate and enforces the firewall allowlists
A79: P-07 | B79: Platform | C79: Day and night mode | D79: Both modes, remembered per browser | E79: All | F79: Both | G79: Live | H79: P3 | I79: Builds it | J79: Each user picks
A80: P-08 | B80: Platform | C80: Demo mode | D80: No sign-in; View as to switch seats | E80: IT | F80: DMZ | G80: Live | H80: P3 | I80: Provides it for demonstrations | J80: Not used in the core: real sign-in only | K80: Not in the core

Sheet Summary
A1: Features by area and status
A3: Area | B3: Live | C3: Extend | D3: Build | E3: Total
A4: Tender intake | B4: =COUNTIFS(Features!$B$2:$B$80,$A4,Features!$G$2:$G$80,"Live") -> 13 | C4: =COUNTIFS(Features!$B$2:$B$80,$A4,Features!$G$2:$G$80,"Extend") -> 2 | D4: =COUNTIFS(Features!$B$2:$B$80,$A4,Features!$G$2:$G$80,"Build") -> 2 | E4: =SUM(B4:D4) -> 17
A5: Bid workspace | B5: =COUNTIFS(Features!$B$2:$B$80,$A5,Features!$G$2:$G$80,"Live") -> 8 | C5: =COUNTIFS(Features!$B$2:$B$80,$A5,Features!$G$2:$G$80,"Extend") -> 0 | D5: =COUNTIFS(Features!$B$2:$B$80,$A5,Features!$G$2:$G$80,"Build") -> 1 | E5: =SUM(B5:D5) -> 9
A6: Design | B6: =COUNTIFS(Features!$B$2:$B$80,$A6,Features!$G$2:$G$80,"Live") -> 12 | C6: =COUNTIFS(Features!$B$2:$B$80,$A6,Features!$G$2:$G$80,"Extend") -> 0 | D6: =COUNTIFS(Features!$B$2:$B$80,$A6,Features!$G$2:$G$80,"Build") -> 0 | E6: =SUM(B6:D6) -> 12
A7: Sizing | B7: =COUNTIFS(Features!$B$2:$B$80,$A7,Features!$G$2:$G$80,"Live") -> 6 | C7: =COUNTIFS(Features!$B$2:$B$80,$A7,Features!$G$2:$G$80,"Extend") -> 0 | D7: =COUNTIFS(Features!$B$2:$B$80,$A7,Features!$G$2:$G$80,"Build") -> 0 | E7: =SUM(B7:D7) -> 6
A8: Finance | B8: =COUNTIFS(Features!$B$2:$B$80,$A8,Features!$G$2:$G$80,"Live") -> 15 | C8: =COUNTIFS(Features!$B$2:$B$80,$A8,Features!$G$2:$G$80,"Extend") -> 0 | D8: =COUNTIFS(Features!$B$2:$B$80,$A8,Features!$G$2:$G$80,"Build") -> 0 | E8: =SUM(B8:D8) -> 15
A9: What-if | B9: =COUNTIFS(Features!$B$2:$B$80,$A9,Features!$G$2:$G$80,"Live") -> 3 | C9: =COUNTIFS(Features!$B$2:$B$80,$A9,Features!$G$2:$G$80,"Extend") -> 1 | D9: =COUNTIFS(Features!$B$2:$B$80,$A9,Features!$G$2:$G$80,"Build") -> 0 | E9: =SUM(B9:D9) -> 4
A10: Evidence | B10: =COUNTIFS(Features!$B$2:$B$80,$A10,Features!$G$2:$G$80,"Live") -> 7 | C10: =COUNTIFS(Features!$B$2:$B$80,$A10,Features!$G$2:$G$80,"Extend") -> 1 | D10: =COUNTIFS(Features!$B$2:$B$80,$A10,Features!$G$2:$G$80,"Build") -> 0 | E10: =SUM(B10:D10) -> 8
A11: Platform | B11: =COUNTIFS(Features!$B$2:$B$80,$A11,Features!$G$2:$G$80,"Live") -> 7 | C11: =COUNTIFS(Features!$B$2:$B$80,$A11,Features!$G$2:$G$80,"Extend") -> 0 | D11: =COUNTIFS(Features!$B$2:$B$80,$A11,Features!$G$2:$G$80,"Build") -> 1 | E11: =SUM(B11:D11) -> 8
A12: Total | B12: =SUM(B4:B11) -> 71 | C12: =SUM(C4:C11) -> 4 | D12: =SUM(D4:D11) -> 4 | E12: =SUM(E4:E11) -> 79
A14: Features by client team
A16: Client team | B16: Features | C16: Live | D16: To build or extend
A17: Legal | B17: =COUNTIF(Features!$E$2:$E$80,$A17) -> 14 | C17: =COUNTIFS(Features!$E$2:$E$80,$A17,Features!$G$2:$G$80,"Live") -> 13 | D17: =B17-C17 -> 1
A18: All | B18: =COUNTIF(Features!$E$2:$E$80,$A18) -> 16 | C18: =COUNTIFS(Features!$E$2:$E$80,$A18,Features!$G$2:$G$80,"Live") -> 13 | D18: =B18-C18 -> 3
A19: Finance | B19: =COUNTIF(Features!$E$2:$E$80,$A19) -> 18 | C19: =COUNTIFS(Features!$E$2:$E$80,$A19,Features!$G$2:$G$80,"Live") -> 18 | D19: =B19-C19 -> 0
A20: IT | B20: =COUNTIF(Features!$E$2:$E$80,$A20) -> 9 | C20: =COUNTIFS(Features!$E$2:$E$80,$A20,Features!$G$2:$G$80,"Live") -> 6 | D20: =B20-C20 -> 3
A21: Projects | B21: =COUNTIF(Features!$E$2:$E$80,$A21) -> 3 | C21: =COUNTIFS(Features!$E$2:$E$80,$A21,Features!$G$2:$G$80,"Live") -> 3 | D21: =B21-C21 -> 0
A22: Management | B22: =COUNTIF(Features!$E$2:$E$80,$A22) -> 5 | C22: =COUNTIFS(Features!$E$2:$E$80,$A22,Features!$G$2:$G$80,"Live") -> 4 | D22: =B22-C22 -> 1
A23: Design | B23: =COUNTIF(Features!$E$2:$E$80,$A23) -> 14 | C23: =COUNTIFS(Features!$E$2:$E$80,$A23,Features!$G$2:$G$80,"Live") -> 14 | D23: =B23-C23 -> 0
A25: Responsibility, in one line
A26: jouleWise | B26: Builds, tests, signs and ships every feature; keeps norms, benchmarks and tender packs current; patches the core under the AMC; supports IT on installation, upgrades and rollback.
A27: Client | B27: Provides the tender documents, inputs, evidence and lender's terms; installs and runs TenderOS on its own hardware; reviews and signs off each step; decides and submits the bid.
